sudoblark_github_cli/__init__.py
sudoblark_github_cli/cli.py
sudoblark_github_cli/console.py
sudoblark_github_cli/constants.py
sudoblark_github_cli/pull_request/__init__.py
sudoblark_github_cli/pull_request/cli.py
sudoblark_github_cli/pull_request/constants.py
sudoblark_github_cli/pull_request/utils.py
sudoblark_github_cli/state.py
sudoblark_github_cli/utils.py
sudoblark_github_cli-1.0.0.dist-info/LICENSE.txt
sudoblark_github_cli-1.0.0.dist-info/METADATA
sudoblark_github_cli-1.0.0.dist-info/WHEEL
sudoblark_github_cli-1.0.0.dist-info/entry_points.txt
sudoblark_github_cli-1.0.0.dist-info/RECORD
