Metadata-Version: 2.3
Name: sudoblark-github-cli
Version: 1.0.0
Summary: A CLI to interact with GitHub, intended to be used for CI/CD operations.
License: BSD-3
Author: Ben Clark
Author-email: bclark@sudoblark.com
Requires-Python: >=3.10.0,<4.0
Classifier: License :: Other/Proprietary License
Classifier: Programming Language :: Python :: 3
Classifier: Programming Language :: Python :: 3.10
Classifier: Programming Language :: Python :: 3.11
Classifier: Programming Language :: Python :: 3.12
Classifier: Programming Language :: Python :: 3.13
Classifier: Topic :: Software Development :: User Interfaces
Requires-Dist: rich (>=13.9.4,<14.0.0)
Requires-Dist: sudoblark_python_core (==1.0.2)
Requires-Dist: typer (>=0.15.1,<0.16.0)
Project-URL: Repository, https://github.com/sudoblark/sudoblark.python.github-cli
